<?xml version = '1.0' encoding = 'UTF-8'?>
<FKIndexAssociation class="oracle.dbtools.crest.model.design.relational.FKIndexAssociation" directorySegmentName="seg_0" id="EF65D7FF-4852-11F5-7A4A-E00CC0D12902" containerWithKeyObject="A925F733-D9E8-DFA6-0A86-297997AC4945" localFKIndex="9C1045AB-3DF9-023D-40D0-1C3E3BADA10E" name="FK_SALE_ISDEL_TYPE">
<sourceConnName>cocoFarm</sourceConnName>
<sourceObjSchema>COCOFARM</sourceObjSchema>
<sourceObjName>FK_SALE_ISDEL_TYPE</sourceObjName>
<createdBy>Sonn</createdBy>
<createdTime>2018-05-31 13:28:51 UTC</createdTime>
<ownerDesignName>cocoFarm physical model design</ownerDesignName>
<referredTableLongName>COCOFARM.ISDEL_TYPE</referredTableLongName>
<deleteRule>NO ACTION</deleteRule>
<referredTableID>1E18596D-27FE-C078-B242-540B9A208511</referredTableID>
<keyObject>5BEFB92F-D993-B363-B47A-AC69F7BDF586</keyObject>
<referredKeyID>5BEFB92F-D993-B363-B47A-AC69F7BDF586</referredKeyID>
<mandatory>true</mandatory>
<refColNames>CODE</refColNames>
<transferable>true</transferable>
<rely>false</rely>
<columnDependencyConstraintGenerateInDDL>true</columnDependencyConstraintGenerateInDDL>
</FKIndexAssociation>