<?xml version = '1.0' encoding = 'UTF-8'?>
<TableProxyOraclev11g class="oracle.dbtools.crest.model.design.storage.oracle.v11g.TableProxyOraclev11g" name="NOTICE" directorySegmentName="seg_0" id="C654D6EE-BF7D-2000-642D-4814AE0F3622">
<createdBy>Sonn</createdBy>
<createdTime>2018-06-17 09:48:03 UTC</createdTime>
<ownerDesignName>cocoDataModel</ownerDesignName>
<schemaObject>5A21A038-32FF-1874-9C45-02C5B0C81981</schemaObject>
<logging>YES</logging>
<partitionedRowMovement>DISABLE</partitionedRowMovement>
<segment>C7995CB2-7513-D59B-D40D-6D6BE371B6AA</segment>
<tableSpace>7011894D-733B-2770-8B36-6B11DFBE2F2D</tableSpace>
<temporaryChanged>false</temporaryChanged>
<accessDriverType>oracle_loader</accessDriverType>
<rejectLimit></rejectLimit>
<columnProxies itemClass="oracle.dbtools.crest.model.design.storage.oracle.v12c.ColumnProxyOraclev12c">
<ColumnProxy name="WRITER_IDX" id="2090BD5A-1FE9-64E5-1EAC-08424E209CFA">
<createdBy>Sonn</createdBy>
<createdTime>2018-06-17 09:48:04 UTC</createdTime>
<ownerDesignName>cocoDataModel</ownerDesignName>
</ColumnProxy>
<ColumnProxy name="TITLE" id="584092B1-DA46-2FD5-7517-DC688ED23F00">
<createdBy>Sonn</createdBy>
<createdTime>2018-06-17 09:48:04 UTC</createdTime>
<ownerDesignName>cocoDataModel</ownerDesignName>
</ColumnProxy>
<ColumnProxy name="WRITTEN_DATE" id="60D3095D-E0D7-17E6-518E-7D7BFF077D9E">
<createdBy>Sonn</createdBy>
<createdTime>2018-06-17 09:48:04 UTC</createdTime>
<ownerDesignName>cocoDataModel</ownerDesignName>
</ColumnProxy>
<ColumnProxy name="CONTENT" id="784D742A-480B-629F-C077-6F1F7BDA17BC">
<createdBy>Sonn</createdBy>
<createdTime>2018-06-17 09:48:04 UTC</createdTime>
<ownerDesignName>cocoDataModel</ownerDesignName>
</ColumnProxy>
<ColumnProxy name="IDX" id="980192BE-276C-6755-FE7F-D7DDFDDF74CA">
<createdBy>Sonn</createdBy>
<createdTime>2018-06-17 09:48:04 UTC</createdTime>
<ownerDesignName>cocoDataModel</ownerDesignName>
</ColumnProxy>
<ColumnProxy name="LAST_EDITED" id="B7442F61-645C-C98F-EBF3-DBCDA2ED4E96">
<createdBy>Sonn</createdBy>
<createdTime>2018-06-17 09:48:04 UTC</createdTime>
<ownerDesignName>cocoDataModel</ownerDesignName>
</ColumnProxy>
</columnProxies>
<indexProxies>
<IndexProxy class="oracle.dbtools.crest.model.design.storage.oracle.v10g.IndexProxyOraclev10g" name="NOTICE_PK" id="96F2BD7F-9C9A-E586-2A89-C488250C5032">
<createdBy>Sonn</createdBy>
<createdTime>2018-06-17 09:48:04 UTC</createdTime>
<ownerDesignName>cocoDataModel</ownerDesignName>
<schemaObject>5A21A038-32FF-1874-9C45-02C5B0C81981</schemaObject>
<segment>43A0F9AB-B9BC-4AED-51C5-AF0C57974A56</segment>
<tableSpace>7011894D-733B-2770-8B36-6B11DFBE2F2D</tableSpace>
</IndexProxy>
</indexProxies>
<foreignKeys>
<ForeignKey class="oracle.dbtools.crest.model.design.storage.oracle.v10g.FKProxyOraclev10g" name="FK_WRITER_IDX_ACC" id="A6400660-5599-898E-27A9-2397CFA4665B">
<createdBy>Sonn</createdBy>
<createdTime>2018-06-17 09:48:04 UTC</createdTime>
<ownerDesignName>cocoDataModel</ownerDesignName>
</ForeignKey>
</foreignKeys>
<primaryKeys>
<PrimaryKey class="oracle.dbtools.crest.model.design.storage.oracle.v10g.PKProxyOraclev10g" name="NOTICE_PK" id="1D89FB2D-15B3-FF24-5315-08AC92C2D787">
<createdBy>Sonn</createdBy>
<createdTime>2018-06-17 09:48:04 UTC</createdTime>
<ownerDesignName>cocoDataModel</ownerDesignName>
<segment>43A0F9AB-B9BC-4AED-51C5-AF0C57974A56</segment>
<tableSpace>7011894D-733B-2770-8B36-6B11DFBE2F2D</tableSpace>
<existingIndex>96F2BD7F-9C9A-E586-2A89-C488250C5032</existingIndex>
<indexSegment>43A0F9AB-B9BC-4AED-51C5-AF0C57974A56</indexSegment>
<indexSort>SORTED</indexSort>
<usingIndex>BY INDEX NAME</usingIndex>
</PrimaryKey>
</primaryKeys>
</TableProxyOraclev11g>